actx/__init__.py
actx/extension.so
actx/include/device.h
actx/include/device_type.h
actx/include/dispatcher.h
actx/include/ilcs/py_devices.h
actx/include/ilcs/py_tensor.h
actx/include/ilcs/py_types.h
actx/include/main.h
actx/include/memory.h
actx/include/memory_pool.h
actx/include/mps.h
actx/include/op_register.h
actx/include/op_types.h
actx/include/storage.h
actx/include/tensor.h
actx/include/tensorbase.h
actx/include/types.h
actx/include/utility.h
actx/kernels.metallib
actx/src/dispatcher.cpp
actx/src/ilcs/py_devices.cpp
actx/src/ilcs/py_dtype.cpp
actx/src/ilcs/py_extension.cpp
actx/src/ilcs/py_tensor.cpp
actx/src/kernels/arithmetic.metal
actx/src/kernels/broadcast.metal
actx/src/kernels/comparisons.metal
actx/src/kernels/init.metal
actx/src/kernels/math_functions.metal
actx/src/main.cpp
actx/src/memory.mm
actx/src/memory_pool.cpp
actx/src/mps.mm
actx/src/op_register.cpp
actx/src/runner.cpp
actx/src/tensor.cpp
actx/src/utility.cpp
actx/tests/add.cpp
actx/tests/broadcast_higher_dims.cpp
actx/tests/broadcast_invalid_shapes.cpp
actx/tests/broadcast_logic.cpp
actx/tests/broadcast_scalar.cpp
actx/tests/broadcast_shapes.cpp
actx/tests/broadcast_single_axes.cpp
actx/tests/dispatcher.cpp
actx/tests/div.cpp
actx/tests/get_dtype_size.cpp
actx/tests/inits.cpp
actx/tests/main.cpp
actx/tests/memory_pool.cpp
actx/tests/misc.cpp
actx/tests/mul.cpp
actx/tests/shape_mismatch.cpp
actx/tests/sub.cpp
actx/tests/tensor_view.cpp
actx-0.1.1.dist-info/METADATA
actx-0.1.1.dist-info/WHEEL
actx-0.1.1.dist-info/licenses/LICENSE
actx-0.1.1.dist-info/RECORD
