Metadata-Version: 2.2
Name: actx
Version: 0.1.1
Summary: High-performance tensor library with NumPy semantics, accelerated on Metal, CUDA, WebGPU, and CPU.
Keywords: tensor,library,numpy,deep-learning,machine-learning,gpu,cuda,metal,webgpu,linear-algebra,autodiff
Author-Email: Arjun Manjunath <dev.arjunmnath@gmail.com>
Maintainer-Email: Arjun Manjunath <dev.arjunmnath@gmail.com>
License: GPL-3.0-or-later
Classifier: Development Status :: 4 - Beta
Classifier: Intended Audience :: Science/Research
Classifier: Intended Audience :: Developers
Classifier: Topic :: Software Development :: Libraries :: Python Modules
Classifier: Topic :: Scientific/Engineering :: Artificial Intelligence
Classifier: Topic :: Scientific/Engineering :: Mathematics
Classifier: Topic :: Software Development :: Libraries
Classifier: License :: OSI Approved :: GNU General Public License v3 (GPLv3)
Classifier: Programming Language :: Python :: 3
Classifier: Programming Language :: Python :: 3.8
Classifier: Programming Language :: Python :: 3.9
Classifier: Programming Language :: Python :: 3.10
Classifier: Programming Language :: Python :: 3.11
Classifier: Programming Language :: Python :: 3.12
Classifier: Programming Language :: C
Classifier: Operating System :: POSIX :: Linux
Classifier: Operating System :: MacOS
Classifier: Operating System :: Microsoft :: Windows
Project-URL: Bug Reports, https://github.com/arjunmnath/act/issues
Project-URL: Source, https://github.com/arjunmnath/act/
Requires-Python: >=3.8
Requires-Dist: numpy
